aioease/__init__.py
aioease/main.py
aioease-0.1.26.dist-info/LICENSE
aioease-0.1.26.dist-info/METADATA
aioease-0.1.26.dist-info/WHEEL
aioease-0.1.26.dist-info/top_level.txt
aioease-0.1.26.dist-info/RECORD
