Metadata-Version: 2.1
Name: aioease
Version: 0.1.26
Summary: A simple and easy way to use asyncio & aiohttp libraries.
License-File: LICENSE
Requires-Dist: aiohttp >=3
Requires-Dist: aiolimiter >=1
